spicedb/__init__.py
spicedb/spicedb.py
spicedb/types.py
spicedb-0.1.0a2.dist-info/LICENSE
spicedb-0.1.0a2.dist-info/METADATA
spicedb-0.1.0a2.dist-info/NOTICE
spicedb-0.1.0a2.dist-info/WHEEL
spicedb-0.1.0a2.dist-info/RECORD
