Metadata-Version: 2.1
Name: spicedb
Version: 0.1.0a2
Summary: An unofficial SpiceDB client for Python.
Home-page: https://spicedb-python.aedge.dev/
Author: Alexander Pushkov
Author-email: ale@aedge.dev
Requires-Python: >=3.12,<4.0
Classifier: Development Status :: 3 - Alpha
Classifier: Framework :: AsyncIO
Classifier: Programming Language :: Python :: 3
Classifier: Programming Language :: Python :: 3.12
Requires-Dist: httpx (>=0.27.0,<0.28.0)
Project-URL: Repository, https://gitlab.com/aedge/spicedb-python
